LICENSE.md
README.md
setup.py
brevo_python/__init__.py
brevo_python/api_client.py
brevo_python/configuration.py
brevo_python/rest.py
brevo_python.egg-info/PKG-INFO
brevo_python.egg-info/SOURCES.txt
brevo_python.egg-info/dependency_links.txt
brevo_python.egg-info/requires.txt
brevo_python.egg-info/top_level.txt
brevo_python/api/__init__.py
brevo_python/api/account_api.py
brevo_python/api/attributes_api.py
brevo_python/api/companies_api.py
brevo_python/api/contacts_api.py
brevo_python/api/conversations_api.py
brevo_python/api/coupons_api.py
brevo_python/api/crm_api.py
brevo_python/api/deals_api.py
brevo_python/api/domains_api.py
brevo_python/api/ecommerce_api.py
brevo_python/api/email_campaigns_api.py
brevo_python/api/events_api.py
brevo_python/api/external_feeds_api.py
brevo_python/api/files_api.py
brevo_python/api/folders_api.py
brevo_python/api/inbound_parsing_api.py
brevo_python/api/lists_api.py
brevo_python/api/master_account_api.py
brevo_python/api/notes_api.py
brevo_python/api/payments_api.py
brevo_python/api/process_api.py
brevo_python/api/reseller_api.py
brevo_python/api/senders_api.py
brevo_python/api/sms_campaigns_api.py
brevo_python/api/tasks_api.py
brevo_python/api/transactional_emails_api.py
brevo_python/api/transactional_sms_api.py
brevo_python/api/transactional_whats_app_api.py
brevo_python/api/user_api.py
brevo_python/api/webhooks_api.py
brevo_python/api/whats_app_campaigns_api.py
brevo_python/api/whatsapp_campaigns_api.py
brevo_python/models/__init__.py
brevo_python/models/ab_test_campaign_result.py
brevo_python/models/ab_test_campaign_result_clicked_links.py
brevo_python/models/ab_test_campaign_result_statistics.py
brevo_python/models/ab_test_version_clicks.py
brevo_python/models/ab_test_version_clicks_inner.py
brevo_python/models/ab_test_version_stats.py
brevo_python/models/add_child_domain.py
brevo_python/models/add_contact_to_list.py
brevo_python/models/add_credits.py
brevo_python/models/authenticate_domain_model.py
brevo_python/models/block_domain.py
brevo_python/models/body.py
brevo_python/models/body1.py
brevo_python/models/body10.py
brevo_python/models/body11.py
brevo_python/models/body12.py
