Metadata-Version: 2.1
Name: brevo-python
Version: 1.1.1
Summary: Brevo API
Home-page: 
Author-email: contact@brevo.com
Keywords: Swagger,Brevo API
License-File: LICENSE.md
Requires-Dist: certifi>=2017.4.17
Requires-Dist: python-dateutil>=2.1
Requires-Dist: six>=1.10
Requires-Dist: urllib3>=1.23
